LICENSE
MANIFEST.in
README.md
README.rst
setup.py
wagtailfacelift/__init__.py
wagtailfacelift/wagtail_hooks.py
wagtailfacelift.egg-info/PKG-INFO
wagtailfacelift.egg-info/SOURCES.txt
wagtailfacelift.egg-info/dependency_links.txt
wagtailfacelift.egg-info/top_level.txt
wagtailfacelift/static/css/facelift.css